sipper.py
sipper_core/__init__.py
sipper_core/auth.py
sipper_core/common.py
sipper_core/compress.py
sipper_core/constants.py
sipper_core/metadata.py
sipper_core/server.py
sipper_core/templates/__init__.py
sipper_core/templates/default/__init__.py
sipper_core/templates/default/debounce.js
sipper_core/templates/default/fzf.umd.js
sipper_core/templates/default/index.html
sipper_core/templates/default/row.html
sipper_core/templates/default/search.html
sipper_core/templates/media/__init__.py
sipper_core/templates/media/debounce.js
sipper_core/templates/media/exif.js
sipper_core/templates/media/fzf.umd.js
sipper_core/templates/media/index.html
sipper_core/templates/media/render.html
sipper_core/templates/media/row.html
sipper_core/templates/media/search.html
static/__init__.py
static/icons.json
static/mime_type_extensions.json
test/__init__.py
test/test.py
test/test-cert/server.crt
test/test-cert/server.key
bottle_sipper-0.1.31.post4.dist-info/METADATA
bottle_sipper-0.1.31.post4.dist-info/WHEEL
bottle_sipper-0.1.31.post4.dist-info/top_level.txt
bottle_sipper-0.1.31.post4.dist-info/RECORD
